arthexis-0.1.33.dist-info/licenses/LICENSE
config/__init__.py
config/active_app.py
config/asgi.py
config/auth_app.py
config/celery.py
config/context_processors.py
config/horologia_app.py
config/loadenv.py
config/logging.py
config/middleware.py
config/offline.py
config/settings.py
config/settings_helpers.py
config/urls.py
config/wsgi.py
core/__init__.py
core/admin.py
core/admin_history.py
core/admindocs.py
core/apps.py
core/auto_upgrade.py
core/auto_upgrade_failover.py
core/backends.py
core/celery_utils.py
core/entity.py
core/environment.py
core/fields.py
core/form_fields.py
core/github_helper.py
core/github_issues.py
core/github_repos.py
core/lcd_screen.py
core/liveupdate.py
core/log_paths.py
core/mailer.py
core/middleware.py
core/models.py
core/notifications.py
core/public_wifi.py
core/reference_utils.py
core/release.py
core/rfid_import_export.py
core/sigil_builder.py
core/sigil_context.py
core/sigil_resolver.py
core/system.py
core/tasks.py
core/temp_passwords.py
core/test_system_info.py
core/tests.py
core/tests_liveupdate.py
core/urls.py
core/user_data.py
core/views.py
core/widgets.py
nodes/__init__.py
nodes/admin.py
nodes/apps.py
nodes/backends.py
nodes/dns.py
nodes/feature_checks.py
nodes/lcd.py
nodes/models.py
nodes/reports.py
nodes/rfid_sync.py
nodes/routing.py
nodes/signals.py
nodes/tasks.py
nodes/tests.py
nodes/urls.py
nodes/utils.py
nodes/views.py
ocpp/__init__.py
ocpp/admin.py
ocpp/apps.py
ocpp/consumers.py
ocpp/evcs.py
ocpp/evcs_discovery.py
ocpp/forwarding_service.py
ocpp/models.py
ocpp/network.py
ocpp/reference_utils.py
ocpp/routing.py
ocpp/simulator.py
ocpp/status_display.py
ocpp/store.py
ocpp/tasks.py
ocpp/test_export_import.py
ocpp/test_rfid.py
ocpp/tests.py
ocpp/transactions_io.py
ocpp/urls.py
ocpp/views.py
ocpp/websocket_headers.py
pages/__init__.py
pages/admin.py
pages/apps.py
pages/checks.py
pages/context_processors.py
pages/defaults.py
pages/forms.py
pages/middleware.py
pages/models.py
pages/module_defaults.py
pages/site_config.py
pages/tasks.py
pages/tests.py
pages/urls.py
arthexis-0.1.33.dist-info/METADATA
arthexis-0.1.33.dist-info/WHEEL
arthexis-0.1.33.dist-info/top_level.txt
arthexis-0.1.33.dist-info/RECORD
