Metadata-Version: 2.4
Name: arthexis
Version: 0.1.33
Summary: Power & Energy Infrastructure
Author-email: "Rafael J. Guillén-Osorio" <tecnologia@gelectriic.com>
License-Expression: GPL-3.0-only
Project-URL: Repository, https://github.com/arthexis/arthexis
Project-URL: Homepage, https://arthexis.com
Classifier: Programming Language :: Python :: 3
Classifier: Framework :: Django
Requires-Python: >=3.10
License-File: LICENSE
Requires-Dist: amqp==5.3.1
Requires-Dist: annotated-types==0.7.0
Requires-Dist: anyio==4.9.0
Requires-Dist: asgiref==3.10.0
Requires-Dist: atproto<0.1.0,>=0.0.63
Requires-Dist: attrs==25.3.0
Requires-Dist: autobahn==24.4.2
Requires-Dist: Automat==25.4.16
Requires-Dist: billiard==4.2.2
Requires-Dist: bleach==6.3.0
Requires-Dist: black==25.11.0
Requires-Dist: celery==5.5.3
Requires-Dist: certifi==2025.10.5
Requires-Dist: cffi==2.0.0
Requires-Dist: channels==4.1.0
Requires-Dist: charset-normalizer==3.4.4
Requires-Dist: click==8.2.1
Requires-Dist: click-didyoumean==0.3.1
Requires-Dist: click-plugins==1.1.1.2
Requires-Dist: click-repl==0.3.0
Requires-Dist: colorama==0.4.6
Requires-Dist: constantly==23.10.4
Requires-Dist: cron-descriptor==2.0.6
Requires-Dist: cryptography==45.0.5
Requires-Dist: daphne==4.2.1
Requires-Dist: diff-match-patch==20241021
Requires-Dist: defusedxml==0.7.1
Requires-Dist: Django==5.2.8
Requires-Dist: django-celery-beat==2.8.1
Requires-Dist: django-debug-toolbar==6.1.0
Requires-Dist: django-import-export==4.3.13
Requires-Dist: django-object-actions==5.0.0
Requires-Dist: django-otp==1.6.3
Requires-Dist: django-timezone-field==7.1
Requires-Dist: dnspython==2.7.0
Requires-Dist: docutils==0.22.2
Requires-Dist: gpiozero==2.0.1; sys_platform == "linux"
Requires-Dist: graphene-django==3.2.3
Requires-Dist: graphviz==0.21
Requires-Dist: geckodriver-autoinstaller==0.1.0
Requires-Dist: h11==0.16.0
Requires-Dist: httpcore==1.0.9
Requires-Dist: httpx==0.28.1
Requires-Dist: hyperlink==21.0.0
Requires-Dist: idna==3.11
Requires-Dist: incremental==24.7.2
Requires-Dist: kombu==5.5.4
Requires-Dist: libipld==3.2.0
Requires-Dist: Markdown==3.9
Requires-Dist: mdx_truly_sane_lists==1.3
Requires-Dist: mfrc522==0.0.7; sys_platform == "linux"
Requires-Dist: outcome==1.3.0.post0
Requires-Dist: packaging==25.0
Requires-Dist: pillow==12.0.0
Requires-Dist: prompt_toolkit==3.0.52
Requires-Dist: psutil==7.1.3
Requires-Dist: psycopg==3.2.9
Requires-Dist: psycopg-binary==3.2.12
Requires-Dist: pyasn1==0.6.1
Requires-Dist: pyasn1_modules==0.4.2
Requires-Dist: pycparser==2.23
Requires-Dist: pydantic==2.12.3
Requires-Dist: pydantic_core==2.41.4
Requires-Dist: pyOpenSSL==25.1.0
Requires-Dist: pyperclip==1.11.0
Requires-Dist: PySocks==1.7.1
Requires-Dist: python-crontab==3.3.0
Requires-Dist: python-dateutil==2.9.0.post0
Requires-Dist: python-dotenv==1.2.1
Requires-Dist: qrcode==8.2
Requires-Dist: redis==7.0.1
Requires-Dist: reportlab==4.4.4
Requires-Dist: requests==2.32.5
Requires-Dist: selenium==4.34.2
Requires-Dist: service-identity==24.2.0
Requires-Dist: setuptools==80.9.0
Requires-Dist: six==1.17.0
Requires-Dist: smbus2==0.5.0
Requires-Dist: sniffio==1.3.1
Requires-Dist: sortedcontainers==2.4.0
Requires-Dist: sqlparse==0.5.3
Requires-Dist: tablib==3.9.0
Requires-Dist: tinycss2==1.4.0
Requires-Dist: toml==0.10.2
Requires-Dist: trio==0.30.0
Requires-Dist: trio-websocket==0.12.2
Requires-Dist: Twisted==25.5.0
Requires-Dist: twine==6.1.0
Requires-Dist: txaio==25.9.2
Requires-Dist: typing-inspection==0.4.2
Requires-Dist: typing_extensions==4.14.1
Requires-Dist: tzdata==2025.2
Requires-Dist: urllib3==2.5.0
Requires-Dist: vine==5.1.0
Requires-Dist: wcwidth==0.2.14
Requires-Dist: webencodings==0.5.1
Requires-Dist: websocket-client==1.8.0
Requires-Dist: websockets==15.0.1
Requires-Dist: whitenoise==6.11.0
Requires-Dist: plyer==2.1.0; sys_platform == "win32"
Requires-Dist: wsproto==1.2.0
Requires-Dist: zope.interface==8.0.1
Dynamic: license-file
